cicpy/__init__.py
cicpy/cic.py
cicpy/aal/aal.py
cicpy/core/__init__.py
cicpy/core/cell.py
cicpy/core/cut.py
cicpy/core/design.py
cicpy/core/graph.py
cicpy/core/guard.py
cicpy/core/instance.py
cicpy/core/instanceport.py
cicpy/core/layer.py
cicpy/core/layoutcell.py
cicpy/core/layoutplacer.py
cicpy/core/point.py
cicpy/core/port.py
cicpy/core/rect.py
cicpy/core/route.py
cicpy/core/routering.py
cicpy/core/rules.py
cicpy/core/text.py
cicpy/eda/__init__.py
cicpy/eda/cellfactory.py
cicpy/eda/magic.py
cicpy/eda/magicdesign.py
cicpy/eda/xschem.py
cicpy/orc/__init__.py
cicpy/orc/orcfile.py
cicpy/place/__init__.py
cicpy/place/placer.py
cicpy/printer/__init__.py
cicpy/printer/cellinfoprinter.py
cicpy/printer/designprinter.py
cicpy/printer/magicprinter.py
cicpy/printer/mcprinter.py
cicpy/printer/skilllayprinter.py
cicpy/printer/skillschprinter.py
cicpy/printer/spiceprinter.py
cicpy/printer/svgprinter.py
cicpy/printer/verilogprinter.py
cicpy/printer/xschemprinter.py
cicpy-0.1.9.dist-info/licenses/LICENSE
cicpy-0.1.9.dist-info/METADATA
cicpy-0.1.9.dist-info/WHEEL
cicpy-0.1.9.dist-info/entry_points.txt
cicpy-0.1.9.dist-info/top_level.txt
cicpy-0.1.9.dist-info/RECORD
