Metadata-Version: 2.4
Name: cicpy
Version: 0.1.9
Summary: Custom IC Creator Python Frontend
Author-email: Carsten Wulff <carsten@wulff.no>
License-Expression: MIT
Project-URL: Homepage, https://github.com/wulffern/cicpy
Project-URL: Bug Tracker, https://github.com/wulffern/cicpy/issues
Classifier: Programming Language :: Python :: 3
Classifier: Operating System :: OS Independent
Requires-Python: >=3.9
License-File: LICENSE
Requires-Dist: numpy
Requires-Dist: pandas
Requires-Dist: svgwrite
Requires-Dist: click
Requires-Dist: pyyaml
Requires-Dist: matplotlib
Requires-Dist: cicspi
Dynamic: license-file
